redmine/__init__.py
redmine/activity.py
redmine/issue.py
redmine/journal.py
redmine/priority.py
redmine/project.py
redmine/query.py
redmine/redmine.py
redmine/time.py
redmine/tracker.py
redmine/user.py
redmine/version.py
redmine/cli/__init__.py
redmine/cli/alias.py
redmine/cli/config.py
redmine/cli/helpers.py
redmine/cli/main.py
redmine/cli/options.py
tests/api/__init__.py
tests/api/response.py
tests/api/test_fetch.py
tests/api/test_get.py
tests/cli/__init__.py
tests/cli/test_cli.py
tests/ui/__init__.py
tests/ui/test_issue.py
tests/ui/test_priority.py
tests/ui/test_project.py
tests/ui/test_query.py
tests/ui/test_tracker.py
tests/ui/test_user.py
redminecli-1.3.0.dist-info/LICENSE
redminecli-1.3.0.dist-info/METADATA
redminecli-1.3.0.dist-info/WHEEL
redminecli-1.3.0.dist-info/entry_points.txt
redminecli-1.3.0.dist-info/top_level.txt
redminecli-1.3.0.dist-info/RECORD
