Metadata-Version: 2.1
Name: redminecli
Version: 1.3.0
Summary: Command line interface for Redmine
Home-page: https://github.com/egegunes/redmine-cli
Author: Ege Güneş
Author-email: egegunes@gmail.com
License: GPLv3
Platform: UNKNOWN
Requires-Dist: requests (>=2.22.0)
Requires-Dist: click (==7.0)
Requires-Dist: colorama (==0.4.1)
